jupyter_server_synchronizer/__init__.py
jupyter_server_synchronizer/_version.py
jupyter_server_synchronizer/gateway.py
jupyter_server_synchronizer/kernel_db.py
jupyter_server_synchronizer/kernel_records.py
jupyter_server_synchronizer/manager.py
jupyter_server_synchronizer/py.typed
jupyter_server_synchronizer/traits.py
jupyter_server_synchronizer-0.0.10.dist-info/METADATA
jupyter_server_synchronizer-0.0.10.dist-info/WHEEL
jupyter_server_synchronizer-0.0.10.dist-info/licenses/COPYING.md
jupyter_server_synchronizer-0.0.10.dist-info/licenses/LICENSE
jupyter_server_synchronizer-0.0.10.dist-info/RECORD
