Metadata-Version: 2.1
Name: jupyter_server_synchronizer
Version: 0.0.10
Summary: A Jupyter Server Session Manager that rehydrates and synchronizes Jupyter sessions (e.g. notebook-kernel connections).
Project-URL: Homepage, https://jupyter-server-synchronizer.readthedocs.io
Project-URL: Documentation, https://jupyter-server-synchronizer.readthedocs.io
Project-URL: Funding, https://numfocus.org/donate
Project-URL: Source, https://github.com/jupyter-server/synchronizer
Project-URL: Tracker, https://github.com/jupyter-server/synchronizer/issues
Author-email: Jupyter Development Team <jupyter@googlegroups.com>
License: # Licensing terms
License-File: COPYING.md
License-File: LICENSE
Keywords: ipython,jupyter
Classifier: Development Status :: 5 - Production/Stable
Classifier: Framework :: Jupyter
Classifier: Intended Audience :: Developers
Classifier: Intended Audience :: Science/Research
Classifier: Intended Audience :: System Administrators
Classifier: License :: OSI Approved :: BSD License
Classifier: Programming Language :: Python
Classifier: Programming Language :: Python :: 3
Classifier: Programming Language :: Python :: 3 :: Only
Requires-Python: >=3.8
Requires-Dist: jupyter-server>=1.21.0
Provides-Extra: test
Requires-Dist: pre-commit; extra == 'test'
Requires-Dist: pytest-jupyter[server]>=0.4.1; extra == 'test'
Requires-Dist: pytest-timeout; extra == 'test'
Requires-Dist: pytest>=7.0; extra == 'test'
